{"contacts":[{"phone":"+38 0505920042","email":{"to":"nmdguru@gmail.com","subject":"A message from the website NOMADGURU Space","body":"Hello, NOMAD GURU!\nI am writing you about _____\n"},"address":{"url":"https://maps.app.goo.gl/uBonwYmUPVY5eScW6","text":"Kyiv, Ukraine"}}],"langs":[{"title":"Українська","code":"uk","url":"/uk/index.html","dir":"uk","locale":"uk-UA"},{"title":"English","code":"en","url":"/en/index.html","dir":"en","locale":"en-GB"},{"title":"Русский","code":"ru","url":"/ru/index.html","dir":"ru","locale":"ru-RU"}],"nav":[{"title":"ART","url":"/uk/art/index.html"},{"title":"HOUSE","url":"/uk/house/index.html"},{"title":"SCHOOl","url":"/uk/school/index.html"},{"title":"ABOUT","url":"/uk/about/index.html"}],"social":["https://www.facebook.com/nmdguru","https://www.instagram.com/nmdguru/","https://www.youtube.com/c/NoMaDGURU","https://soundcloud.com/nomad-guru","https://t.me/nomadguru"],"structure":[{"title":"HOME"},{"title":"ART (Music and Visual)","children":[{"title":"TONES of MIND ( album )"},{"title":"THE WAY Саги про життя","children":["Verbovaya","River in Me","HOLODY","Sat Kar TAr","SYLA","V Krapli"]}]},{"title":"HOUSE (Music Retreat Centre)","children":["Студия Звукозапису","Лазня - Хостел"]},{"title":"SCHOOL","children":["Vocal Trening з Террою","Подих Єднання","Майстри","Стати учасником"]},{"title":"ABOUT","children":[{"title":"CONTACTS","children":["Youtube","Instagram","Facebook","Telegram"]}]}]}